[
  {
    "Number": "120"
  },
  {
    "Number": "121"
  },
  {
    "Number": "122"
  },
  {
    "Number": "123"
  },
  {
    "Number": "124"
  },
  {
    "Number": "125"
  },
  {
    "Number": "126"
  },
  {
    "Number": "127"
  },
  {
    "Number": "128"
  },
  {
    "Number": "129"
  },
  {
    "Number": "130"
  },
  {
    "Number": "131"
  },
  {
    "Number": "132"
  },
  {
    "Number": "133"
  },
  {
    "Number": "134"
  },
  {
    "Number": "135"
  },
  {
    "Number": "136"
  },
  {
    "Number": "137"
  }
]